odoo/addons/stock_cycle_count/README.rst
odoo/addons/stock_cycle_count/__init__.py
odoo/addons/stock_cycle_count/__manifest__.py
odoo/addons/stock_cycle_count/data/cycle_count_ir_cron.xml
odoo/addons/stock_cycle_count/data/cycle_count_sequence.xml
odoo/addons/stock_cycle_count/i18n/am.po
odoo/addons/stock_cycle_count/i18n/ar.po
odoo/addons/stock_cycle_count/i18n/bg.po
odoo/addons/stock_cycle_count/i18n/bs.po
odoo/addons/stock_cycle_count/i18n/ca.po
odoo/addons/stock_cycle_count/i18n/ca_ES.po
odoo/addons/stock_cycle_count/i18n/cs.po
odoo/addons/stock_cycle_count/i18n/da.po
odoo/addons/stock_cycle_count/i18n/de.po
odoo/addons/stock_cycle_count/i18n/el_GR.po
odoo/addons/stock_cycle_count/i18n/en_AU.po
odoo/addons/stock_cycle_count/i18n/en_GB.po
odoo/addons/stock_cycle_count/i18n/es.po
odoo/addons/stock_cycle_count/i18n/es_AR.po
odoo/addons/stock_cycle_count/i18n/es_CL.po
odoo/addons/stock_cycle_count/i18n/es_CO.po
odoo/addons/stock_cycle_count/i18n/es_CR.po
odoo/addons/stock_cycle_count/i18n/es_DO.po
odoo/addons/stock_cycle_count/i18n/es_EC.po
odoo/addons/stock_cycle_count/i18n/es_ES.po
odoo/addons/stock_cycle_count/i18n/es_MX.po
odoo/addons/stock_cycle_count/i18n/es_PE.po
odoo/addons/stock_cycle_count/i18n/es_PY.po
odoo/addons/stock_cycle_count/i18n/es_VE.po
odoo/addons/stock_cycle_count/i18n/et.po
odoo/addons/stock_cycle_count/i18n/eu.po
odoo/addons/stock_cycle_count/i18n/fa.po
odoo/addons/stock_cycle_count/i18n/fi.po
odoo/addons/stock_cycle_count/i18n/fr.po
odoo/addons/stock_cycle_count/i18n/fr_CA.po
odoo/addons/stock_cycle_count/i18n/fr_CH.po
odoo/addons/stock_cycle_count/i18n/fr_FR.po
odoo/addons/stock_cycle_count/i18n/gl.po
odoo/addons/stock_cycle_count/i18n/gl_ES.po
odoo/addons/stock_cycle_count/i18n/he.po
odoo/addons/stock_cycle_count/i18n/hi.po
odoo/addons/stock_cycle_count/i18n/hr.po
odoo/addons/stock_cycle_count/i18n/hr_HR.po
odoo/addons/stock_cycle_count/i18n/hu.po
odoo/addons/stock_cycle_count/i18n/id.po
odoo/addons/stock_cycle_count/i18n/it.po
odoo11_addon_stock_cycle_count-11.0.1.0.2.dist-info/METADATA
odoo11_addon_stock_cycle_count-11.0.1.0.2.dist-info/WHEEL
odoo11_addon_stock_cycle_count-11.0.1.0.2.dist-info/top_level.txt
odoo11_addon_stock_cycle_count-11.0.1.0.2.dist-info/RECORD
